reassembler/__init__.py
reassembler/__main__.py
reassembler/reassembler.py
reassembler-2.1.1.dist-info/METADATA
reassembler-2.1.1.dist-info/WHEEL
reassembler-2.1.1.dist-info/entry_points.txt
reassembler-2.1.1.dist-info/top_level.txt
reassembler-2.1.1.dist-info/RECORD
