Metadata-Version: 2.1
Name: reassembler
Version: 2.1.1
Summary: Reassemble overlapping fragments into new pcaps with different OS reassembly policies.
Home-page: https://github.com/markbaggett/reassembler
Author: MarkBaggett
Author-email: lo127001@gmail.com
License: GNU General Public License v3 (GPLv3
Platform: UNKNOWN
Classifier: Programming Language :: Python :: 3
Classifier: License :: OSI Approved :: GNU General Public License v3 (GPLv3)
Classifier: Operating System :: OS Independent
Requires-Python: >=3.6
Requires-Dist: scapy (==2.4.4)
